tabtune/__init__.py
tabtune/logger.py
tabtune/run.py
tabtune/Dataprocess/__init__.py
tabtune/Dataprocess/contexttab_preprocessor.py
tabtune/Dataprocess/data_processor.py
tabtune/Dataprocess/limix_preprocessor.py
tabtune/Dataprocess/mitra_preprocessor.py
tabtune/Dataprocess/orion_bix_preprocessor.py
tabtune/Dataprocess/orion_msp_preprocessor.py
tabtune/Dataprocess/tabdpt_preprocessor.py
tabtune/Dataprocess/tabicl_preprocessor.py
tabtune/Dataprocess/tabpfn_preprocessor.py
tabtune/TabularLeaderboard/__init__.py
tabtune/TabularLeaderboard/leaderboard.py
tabtune/TabularPipeline/__init__.py
tabtune/TabularPipeline/pipeline.py
tabtune/TuningManager/__init__.py
tabtune/TuningManager/peft_utils.py
tabtune/TuningManager/peft_utils_trial.py
tabtune/TuningManager/tuning.py
tabtune/benchmarking/__init__.py
tabtune/benchmarking/benchmark_pipeline.py
tabtune/benchmarking/benchmarking_config.py
tabtune/benchmarking/result_handler.py
tabtune/data/base.py
tabtune/data/extract_tabzilla_ids.py
tabtune/data/openml.py
tabtune/data/tabarena.py
tabtune/data/tabzilla.py
tabtune/data/talent_full.py
tabtune/models/__init__.py
tabtune/models/apt/__init__.py
tabtune/models/apt/utils.py
tabtune/models/apt/data/__init__.py
tabtune/models/apt/data/base.py
tabtune/models/apt/data/mlp.py
tabtune/models/apt/data/utils.py
tabtune/models/apt/data/wrapper.py
tabtune/models/apt/model/__init__.py
tabtune/models/apt/model/attention.py
tabtune/models/apt/model/convolution.py
tabtune/models/apt/model/feedforward.py
tabtune/models/apt/model/model.py
tabtune/models/apt/model/transformer.py
tabtune/models/apt/model/utils.py
tabtune/models/apt/model/wrapper.py
tabtune/models/apt/train/__init__.py
tabtune/models/apt/train/train.py
tabtune/models/apt/train/utils.py
tabtune/models/contexttab/__init__.py
tabtune/models/contexttab/attention.py
tabtune/models/contexttab/constants.py
tabtune/models/contexttab/contexttab.py
tabtune/models/contexttab/embeddings.py
tabtune/models/contexttab/torch_model.py
tabtune-0.1.5.dist-info/licenses/LICENSE
tabtune-0.1.5.dist-info/METADATA
tabtune-0.1.5.dist-info/WHEEL
tabtune-0.1.5.dist-info/top_level.txt
tabtune-0.1.5.dist-info/RECORD
