Metadata-Version: 2.4
Name: tabtune
Version: 0.1.5
Summary: TabTune: A Unified Library for Inference and Fine-Tuning Tabular Foundation Models
Home-page: https://github.com/Lexsi-Labs/TabTune
Author: Aditya Tanna, Pratinav Seth, Mohamed Bouadi, Utsav Avaiya, Vinay Kumar Sankarapu
Author-email: Aditya Tanna <aditya.tanna@lexsi.ai>, Pratinav Seth <pratinav.seth@lexsi.ai>, Mohamed Bouadi <mohamed.bouadi@lexsi.ai>, Utsav Avaiya <utsav.avaiya@lexsi.ai>, Vinay Kumar Sankarapu <v.k@lexsi.ai>
Maintainer: Aditya Tanna
Maintainer-email: Aditya Tanna <aditya.tanna@lexsi.ai>
License: MIT
Project-URL: Homepage, https://github.com/Lexsi-Labs/TabTune
Project-URL: Repository, https://github.com/Lexsi-Labs/TabTune
Project-URL: Issues, https://github.com/Lexsi-Labs/TabTune/issues
Keywords: tabular-data,machine-learning,model-adaptation,pytorch,scikit-learn
Classifier: Development Status :: 3 - Alpha
Classifier: Programming Language :: Python :: 3
Classifier: Programming Language :: Python :: 3.10
Classifier: Programming Language :: Python :: 3.11
Classifier: Programming Language :: Python :: 3.12
Classifier: License :: OSI Approved :: MIT License
Classifier: Operating System :: OS Independent
Classifier: Intended Audience :: Science/Research
Classifier: Topic :: Scientific/Engineering :: Artificial Intelligence
Requires-Python: >=3.10
License-File: LICENSE
Requires-Dist: torch>=2.7.0
Requires-Dist: torchvision>=0.22.0
Requires-Dist: torchaudio>=2.7.0
Requires-Dist: transformers<5.0.0,>=4.56.0
Requires-Dist: scikit-learn>=1.6.0
Requires-Dist: pandas<2.4.0,>=2.2.0
Requires-Dist: pyzmq<28.0.0,>=25.0.0
Requires-Dist: numpy<3.0.0,>=1.26.0
Requires-Dist: joblib>=1.0.0
Requires-Dist: openml>=0.12.0
Requires-Dist: tqdm>=4.60.0
Requires-Dist: category_encoders>=2.0.0
Requires-Dist: imbalanced-learn>=0.8.0
Requires-Dist: sentence-transformers<3.0.0,>=2.0.0
Requires-Dist: huggingface_hub>=0.10.0
Requires-Dist: einops>=0.6.0
Requires-Dist: pydantic<3.0.0,>=1.8.0
Requires-Dist: pydantic_settings>=2.0.0
Requires-Dist: safetensors>=0.3.0
Requires-Dist: omegaconf>=2.1.0
Requires-Dist: psutil>=5.8.0
Requires-Dist: torcheval>=0.0.6
Requires-Dist: faiss-cpu>=1.7.0
Requires-Dist: colorlog>=6.0.0
Requires-Dist: einx>=0.3.0
Requires-Dist: fairlearn>=0.13.0
Requires-Dist: gdown>=5.0.0
Requires-Dist: python-json-logger>=2.0.0
Requires-Dist: rich>=13.0.0
Provides-Extra: dev
Requires-Dist: pytest>=7.0.0; extra == "dev"
Requires-Dist: pytest-cov>=4.0.0; extra == "dev"
Requires-Dist: pytest-mock>=3.10.0; extra == "dev"
Requires-Dist: pytest-xdist>=3.0.0; extra == "dev"
Requires-Dist: black>=23.0.0; extra == "dev"
Requires-Dist: isort>=5.12.0; extra == "dev"
Requires-Dist: flake8>=6.0.0; extra == "dev"
Requires-Dist: pre-commit>=3.0.0; extra == "dev"
Provides-Extra: interactive
Requires-Dist: IPython>=8.0.0; extra == "interactive"
Provides-Extra: colab
Requires-Dist: ipython==7.34.0; extra == "colab"
Requires-Dist: numpy>=2.0.0; extra == "colab"
Requires-Dist: pandas==2.2.2; extra == "colab"
Requires-Dist: scikit-learn==1.6.1; extra == "colab"
Provides-Extra: strict
Requires-Dist: torch==2.7.0; extra == "strict"
Requires-Dist: torchvision==0.22.0; extra == "strict"
Requires-Dist: torchaudio==2.7.0; extra == "strict"
Requires-Dist: transformers==4.56.0; extra == "strict"
Requires-Dist: scikit-learn==1.7.0; extra == "strict"
Requires-Dist: pyzmq==27.0.1; extra == "strict"
Dynamic: author
Dynamic: home-page
Dynamic: license-file
Dynamic: maintainer
Dynamic: requires-python
